datasette_ersatz_table_valued_functions/__init__.py
datasette_ersatz_table_valued_functions-0.2.dist-info/LICENSE
datasette_ersatz_table_valued_functions-0.2.dist-info/METADATA
datasette_ersatz_table_valued_functions-0.2.dist-info/WHEEL
datasette_ersatz_table_valued_functions-0.2.dist-info/entry_points.txt
datasette_ersatz_table_valued_functions-0.2.dist-info/top_level.txt
datasette_ersatz_table_valued_functions-0.2.dist-info/RECORD
