Metadata-Version: 2.1
Name: datasette-ersatz-table-valued-functions
Version: 0.2
Summary: Enable a limited form of table-valued functions.
Home-page: https://github.com/cldellow/datasette-ersatz-table-valued-functions
Author: Colin Dellow
License: Apache License, Version 2.0
Project-URL: Issues, https://github.com/cldellow/datasette-ersatz-table-valued-functions/issues
Project-URL: CI, https://github.com/cldellow/datasette-ersatz-table-valued-functions/actions
Project-URL: Changelog, https://github.com/cldellow/datasette-ersatz-table-valued-functions/releases
Classifier: Framework :: Datasette
Classifier: License :: OSI Approved :: Apache Software License
Requires-Python: >=3.7
License-File: LICENSE
Requires-Dist: datasette
Requires-Dist: ersatz-table-valued-functions
Requires-Dist: datasette-rewrite-sql
Provides-Extra: test
Requires-Dist: pytest ; extra == 'test'
Requires-Dist: pytest-asyncio ; extra == 'test'
Requires-Dist: pytest-watch ; extra == 'test'
